webify/_version.py
tljh_webify-0.1.0.data/data/share/jupyter/labextensions/webify/install.json
tljh_webify-0.1.0.dist-info/METADATA
tljh_webify-0.1.0.dist-info/WHEEL
tljh_webify-0.1.0.dist-info/licenses/LICENSE
tljh_webify-0.1.0.dist-info/RECORD
