Metadata-Version: 2.3
Name: tljh-webify
Version: 0.1.0
Summary: A JupyterLab extension to copy files from a jupyter lab user folder to a different folder (to be served on a web)
Project-URL: Homepage, https://github.com/ICTSoEasy/webify
Project-URL: Bug Tracker, https://github.com/ICTSoEasy/webify/issues
Project-URL: Repository, https://github.com/ICTSoEasy/webify.git
Author-email: Oli Howson <oli.howson@open.ac.uk>
License: BSD 3-Clause License
License-File: LICENSE
Keywords: jupyter,jupyterlab,jupyterlab-extension
Classifier: Framework :: Jupyter
Classifier: Framework :: Jupyter :: JupyterLab
Classifier: Framework :: Jupyter :: JupyterLab :: 4
Classifier: Framework :: Jupyter :: JupyterLab :: Extensions
Classifier: Framework :: Jupyter :: JupyterLab :: Extensions :: Prebuilt
Classifier: License :: OSI Approved :: BSD License
Classifier: Programming Language :: Python
Classifier: Programming Language :: Python :: 3
Classifier: Programming Language :: Python :: 3.8
Classifier: Programming Language :: Python :: 3.9
Classifier: Programming Language :: Python :: 3.10
Classifier: Programming Language :: Python :: 3.11
Classifier: Programming Language :: Python :: 3.12
Requires-Python: >=3.8
